{"py/object": "rasa.core.featurizers.tracker_featurizers.IntentMaxHistoryTrackerFeaturizer", "state_featurizer": {"py/object": "rasa.core.featurizers.single_state_featurizer.IntentTokenizerSingleStateFeaturizer", "_default_feature_states": {"intent": {"are_you_a_bot": 0, "automatic_bill_payments": 1, "back": 2, "bot_challenge": 3, "credit_card_requirements": 4, "dispute_transaction": 5, "goodbye": 6, "greet": 7, "mobile_check_deposit": 8, "nlu_fallback": 9, "open_account": 10, "out_of_scope": 11, "reset_password": 12, "restart": 13, "savings_account_interest_rate": 14, "session_start": 15, "transfer_funds": 16, "wire_transfer_fees": 17, "withdrawal_limit": 18}, "action_name": {"action_listen": 0, "action_restart": 1, "action_session_start": 2, "action_default_fallback": 3, "action_deactivate_loop": 4, "action_revert_fallback_events": 5, "action_default_ask_affirmation": 6, "action_default_ask_rephrase": 7, "action_two_stage_fallback": 8, "action_unlikely_intent": 9, "action_back": 10, "...": 11, "action_extract_slots": 12, "utter_automatic_bill_payments": 13, "utter_credit_card_requirements": 14, "utter_default_response": 15, "utter_dispute_transaction": 16, "utter_goodbye": 17, "utter_greet": 18, "utter_iamabot": 19, "utter_mobile_check_deposit": 20, "utter_open_account": 21, "utter_out_of_scope": 22, "utter_reset_password": 23, "utter_savings_account_interest_rate": 24, "utter_transfer_funds": 25, "utter_wire_transfer_fees": 26, "utter_withdrawal_limit": 27}, "entities": {}, "slots": {}, "active_loop": {}}, "action_texts": [], "entity_tag_specs": []}, "max_history": 5, "remove_duplicates": true}